eppo_metrics_sync/__init__.py
eppo_metrics_sync/__main__.py
eppo_metrics_sync/dbt_model_parser.py
eppo_metrics_sync/eppo_metrics_sync.py
eppo_metrics_sync/helper.py
eppo_metrics_sync/validation.py
eppo_metrics_sync/schema/eppo_metric_schema.json
eppo_metrics_sync-0.1.15.dist-info/licenses/LICENSE
eppo_metrics_sync-0.1.15.dist-info/METADATA
eppo_metrics_sync-0.1.15.dist-info/WHEEL
eppo_metrics_sync-0.1.15.dist-info/top_level.txt
eppo_metrics_sync-0.1.15.dist-info/RECORD
