Metadata-Version: 2.4
Name: eppo_metrics_sync
Version: 0.1.15
Summary: Sync metrics to Eppo
Requires-Python: >=3.7
License-File: LICENSE
Requires-Dist: PyYAML
Requires-Dist: jsonschema
Requires-Dist: requests
Dynamic: license-file
